{
	"aries": {
		"symbol": "♈",
		"dateMin": "2000-03-21",
		"dateMax": "2000-04-20",
		 "modality": "Cardinal",
     		 "opposite": "Libra"
	},
	"taurus": {
		"symbol": "♉",
		"dateMin": "2000-04-21",
		"dateMax": "2000-05-21",
     		"modality": "Fixed",
      		"opposite": "Scorpio"
	},
	"gemini": {
		"symbol": "♊",
		"dateMin": "2000-05-22",
		"dateMax": "2000-06-21",
    		"modality": "Mutable",
    	        "opposite": "Sagittarius"
	},
	"cancer": {
		"symbol": "♋",
		"dateMin": "2000-06-22",
		"dateMax": "2000-07-22",
     		"modality": "Cardinal",
     		"opposite": "Capricorn"
	},
	"leo": {
		"symbol": "♌",
		"dateMin": "2000-07-23",
		"dateMax": "2000-08-22",
      		"modality": "Fixed",
     	 	"opposite": "Aquarius"
	},
	"virgo": {
		"symbol": "♍",
		"dateMin": "2000-08-23",
		"dateMax": "2000-09-23",
      		"modality": "Mutable",
      		"opposite": "Pisces"
	},
	"libra": {
		"symbol": "♎",
		"dateMin": "2000-09-24",
		"dateMax": "2000-10-23",
     		"modality": "Cardinal",
      		"opposite": "Aries"
	},
	"scorpio": {
		"symbol": "♏",
		"dateMin": "2000-10-24",
		"dateMax": "2000-11-22",
      		"modality": "Fixed",
     		"opposite": "Taurus"
	},
	"sagittarius": {
		"symbol": "♐",
		"dateMin": "2000-11-23",
		"dateMax": "2000-12-21",
     		"modality": "Mutable",
     		"opposite": "Gemini"
	},
	"capricorn": {
		"symbol": "♑",
		"dateMin": "2000-12-22",
		"dateMax": "2000-01-20",
      		"modality": "Cardinal",
      		"opposite": "Cancer"
	},
	"aquarius": {
		"symbol": "♒",
		"dateMin": "2000-01-21",
		"dateMax": "2000-02-19",
     		"modality": "Fixed",
      		"opposite": "Leo"
	},
	"pisces": {
		"symbol": "♓",
		"dateMin": "2000-02-20",
		"dateMax": "2000-03-20",
      		"modality": "Mutable",
      		"opposite": "Virgo"
	}
}
